patlib/__init__.py
patlib/sci.py
patlib/std.py
patlib-0.3.7.dist-info/METADATA
patlib-0.3.7.dist-info/WHEEL
patlib-0.3.7.dist-info/RECORD
